charset_project/__init__.py
charset_project/charset.py
chars-0.1.2.dist-info/LICENSE.txt
chars-0.1.2.dist-info/METADATA
chars-0.1.2.dist-info/WHEEL
chars-0.1.2.dist-info/top_level.txt
chars-0.1.2.dist-info/RECORD
