Metadata-Version: 2.1
Name: chars
Version: 0.1.2
Summary: A package for character sets
Author: PiyushThePal
Author-email: cool_guy2331708@yahoo.com
Classifier: Programming Language :: Python :: 3
Classifier: License :: OSI Approved :: MIT License
Classifier: Operating System :: OS Independent
Requires-Python: >=3.6
License-File: LICENSE.txt
